jenkins_manager/__init.py__
jenkins_manager/runJob.py
jenkins_manager/Jenkins/Client.py
jenkins_manager-0.1.3.dist-info/METADATA
jenkins_manager-0.1.3.dist-info/WHEEL
jenkins_manager-0.1.3.dist-info/entry_points.txt
jenkins_manager-0.1.3.dist-info/licenses/LICENSE
jenkins_manager-0.1.3.dist-info/RECORD
