Metadata-Version: 2.3
Name: jenkins-manager
Version: 0.1.3
Summary: python package to drive jenkins
Author: Tom Wilson
License-File: LICENSE
Classifier: License :: OSI Approved :: MIT License
Classifier: Operating System :: OS Independent
Classifier: Programming Language :: Python :: 3
Requires-Python: >=3.4
Requires-Dist: requests
